{
    "header_linie": null,
    "segmente": [
        {
            "zaehler": "0010",
            "nr": "00001",
            "bezeichnung": "UNH",
            "standard_status": "M",
            "bdew_status": "M",
            "standard_maximale_wiederholungen": 1,
            "bdew_maximale_wiederholungen": 1,
            "ebene": 0,
            "inhalt": "Nachrichten-Kopfsegment"
        },
        {
            "zaehler": "0020",
            "nr": "00002",
            "bezeichnung": "BGM",
            "standard_status": "M",
            "bdew_status": "M",
            "standard_maximale_wiederholungen": 1,
            "bdew_maximale_wiederholungen": 1,
            "ebene": 0,
            "inhalt": "Beginn der Nachricht"
        },
        {
            "zaehler": "0030",
            "nr": "00003",
            "bezeichnung": "DTM",
            "standard_status": "M",
            "bdew_status": "M",
            "standard_maximale_wiederholungen": 35,
            "bdew_maximale_wiederholungen": 1,
            "ebene": 1,
            "inhalt": "Nachrichtendatum"
        },
        {
            "zaehler": "0030",
            "nr": "00004",
            "bezeichnung": "DTM",
            "standard_status": "M",
            "bdew_status": "D",
            "standard_maximale_wiederholungen": 35,
            "bdew_maximale_wiederholungen": 1,
            "ebene": 1,
            "inhalt": "Ausf\u00fchrungsdatum"
        },
        {
            "zaehler": "0030",
            "nr": "00005",
            "bezeichnung": "DTM",
            "standard_status": "M",
            "bdew_status": "D",
            "standard_maximale_wiederholungen": 35,
            "bdew_maximale_wiederholungen": 1,
            "ebene": 1,
            "inhalt": "verschobener Abmeldetermin"
        },
        {
            "zaehler": "0030",
            "nr": "00006",
            "bezeichnung": "DTM",
            "standard_status": "M",
            "bdew_status": "D",
            "standard_maximale_wiederholungen": 35,
            "bdew_maximale_wiederholungen": 1,
            "ebene": 1,
            "inhalt": "geplanter Behebungszeitpunkt"
        },
        {
            "zaehler": "0060",
            "nr": "00007",
            "bezeichnung": "IMD",
            "standard_status": "C",
            "bdew_status": "D",
            "standard_maximale_wiederholungen": 999,
            "bdew_maximale_wiederholungen": 1,
            "ebene": 1,
            "inhalt": "Abonnement"
        },
        {
            "zaehler": "0060",
            "nr": "00008",
            "bezeichnung": "IMD",
            "standard_status": "C",
            "bdew_status": "D",
            "standard_maximale_wiederholungen": 999,
            "bdew_maximale_wiederholungen": 1,
            "ebene": 1,
            "inhalt": "Produkt-/Leistungsbeschreibung"
        },
        {
            "zaehler": "2400",
            "nr": "00026",
            "bezeichnung": "UNS",
            "standard_status": "M",
            "bdew_status": "M",
            "standard_maximale_wiederholungen": 1,
            "bdew_maximale_wiederholungen": 1,
            "ebene": 0,
            "inhalt": "Abschnitts-Kontrollsegment"
        },
        {
            "zaehler": "2410",
            "nr": "00027",
            "bezeichnung": "MOA",
            "standard_status": "C",
            "bdew_status": "D",
            "standard_maximale_wiederholungen": 12,
            "bdew_maximale_wiederholungen": 1,
            "ebene": 1,
            "inhalt": "Mindestbetrag (netto) der Kosten einer Sperrung"
        },
        {
            "zaehler": "2410",
            "nr": "00028",
            "bezeichnung": "MOA",
            "standard_status": "C",
            "bdew_status": "D",
            "standard_maximale_wiederholungen": 12,
            "bdew_maximale_wiederholungen": 1,
            "ebene": 1,
            "inhalt": "H\u00f6chstbetrag (netto) der Kosten einer Sperrung"
        },
        {
            "zaehler": "2470",
            "nr": "00029",
            "bezeichnung": "UNT",
            "standard_status": "M",
            "bdew_status": "M",
            "standard_maximale_wiederholungen": 1,
            "bdew_maximale_wiederholungen": 1,
            "ebene": 0,
            "inhalt": "Nachrichten-Endesegment"
        }
    ],
    "segmentgruppen": [
        {
            "header_linie": {
                "zaehler": "0090",
                "nr": null,
                "bezeichnung": "SG1",
                "standard_status": "C",
                "bdew_status": "D",
                "standard_maximale_wiederholungen": 9999,
                "bdew_maximale_wiederholungen": 1,
                "ebene": 1,
                "inhalt": "Referenz der Anfrage/Bestellung/Stornierung"
            },
            "segmente": [
                {
                    "zaehler": "0100",
                    "nr": "00009",
                    "bezeichnung": "RFF",
                    "standard_status": "M",
                    "bdew_status": "M",
                    "standard_maximale_wiederholungen": 1,
                    "bdew_maximale_wiederholungen": 1,
                    "ebene": 1,
                    "inhalt": "Referenz Nachrichtennummer"
                }
            ],
            "segmentgruppen": []
        },
        {
            "header_linie": {
                "zaehler": "0090",
                "nr": null,
                "bezeichnung": "SG1",
                "standard_status": "C",
                "bdew_status": "D",
                "standard_maximale_wiederholungen": 9999,
                "bdew_maximale_wiederholungen": 1,
                "ebene": 1,
                "inhalt": "Referenz einer vorangegangenen Nachricht"
            },
            "segmente": [
                {
                    "zaehler": "0100",
                    "nr": "00010",
                    "bezeichnung": "RFF",
                    "standard_status": "M",
                    "bdew_status": "M",
                    "standard_maximale_wiederholungen": 1,
                    "bdew_maximale_wiederholungen": 1,
                    "ebene": 1,
                    "inhalt": "Referenz einer vorangegangenen Nachricht"
                }
            ],
            "segmentgruppen": []
        },
        {
            "header_linie": {
                "zaehler": "0090",
                "nr": null,
                "bezeichnung": "SG1",
                "standard_status": "C",
                "bdew_status": "D",
                "standard_maximale_wiederholungen": 9999,
                "bdew_maximale_wiederholungen": 1,
                "ebene": 1,
                "inhalt": "Referenz Vorgangsnummer"
            },
            "segmente": [
                {
                    "zaehler": "0100",
                    "nr": "00011",
                    "bezeichnung": "RFF",
                    "standard_status": "M",
                    "bdew_status": "M",
                    "standard_maximale_wiederholungen": 1,
                    "bdew_maximale_wiederholungen": 1,
                    "ebene": 1,
                    "inhalt": "Referenz Vorgangsnummer"
                }
            ],
            "segmentgruppen": []
        },
        {
            "header_linie": {
                "zaehler": "0090",
                "nr": null,
                "bezeichnung": "SG1",
                "standard_status": "C",
                "bdew_status": "R",
                "standard_maximale_wiederholungen": 9999,
                "bdew_maximale_wiederholungen": 1,
                "ebene": 1,
                "inhalt": "Pr\u00fcfidentifikator"
            },
            "segmente": [
                {
                    "zaehler": "0100",
                    "nr": "00012",
                    "bezeichnung": "RFF",
                    "standard_status": "M",
                    "bdew_status": "M",
                    "standard_maximale_wiederholungen": 1,
                    "bdew_maximale_wiederholungen": 1,
                    "ebene": 1,
                    "inhalt": "Pr\u00fcfidentifikator"
                }
            ],
            "segmentgruppen": []
        },
        {
            "header_linie": {
                "zaehler": "0120",
                "nr": null,
                "bezeichnung": "SG2",
                "standard_status": "C",
                "bdew_status": "D",
                "standard_maximale_wiederholungen": 1,
                "bdew_maximale_wiederholungen": 1,
                "ebene": 1,
                "inhalt": "Antwortkategorie"
            },
            "segmente": [
                {
                    "zaehler": "0130",
                    "nr": "00013",
                    "bezeichnung": "AJT",
                    "standard_status": "M",
                    "bdew_status": "M",
                    "standard_maximale_wiederholungen": 1,
                    "bdew_maximale_wiederholungen": 1,
                    "ebene": 1,
                    "inhalt": "Einzelheiten zu einer Anpassung/\u00c4nderung"
                },
                {
                    "zaehler": "0140",
                    "nr": "00014",
                    "bezeichnung": "FTX",
                    "standard_status": "C",
                    "bdew_status": "D",
                    "standard_maximale_wiederholungen": 5,
                    "bdew_maximale_wiederholungen": 1,
                    "ebene": 2,
                    "inhalt": "Allgemeine Information (Feld f\u00fcr allgemeine Hinweise)"
                }
            ],
            "segmentgruppen": []
        },
        {
            "header_linie": {
                "zaehler": "0150",
                "nr": null,
                "bezeichnung": "SG3",
                "standard_status": "C",
                "bdew_status": "R",
                "standard_maximale_wiederholungen": 99,
                "bdew_maximale_wiederholungen": 1,
                "ebene": 1,
                "inhalt": "MP-ID Absender"
            },
            "segmente": [
                {
                    "zaehler": "0160",
                    "nr": "00015",
                    "bezeichnung": "NAD",
                    "standard_status": "M",
                    "bdew_status": "M",
                    "standard_maximale_wiederholungen": 1,
                    "bdew_maximale_wiederholungen": 1,
                    "ebene": 1,
                    "inhalt": "MP-ID Absender"
                }
            ],
            "segmentgruppen": [
                {
                    "header_linie": {
                        "zaehler": "0250",
                        "nr": null,
                        "bezeichnung": "SG6",
                        "standard_status": "C",
                        "bdew_status": "D",
                        "standard_maximale_wiederholungen": 5,
                        "bdew_maximale_wiederholungen": 1,
                        "ebene": 2,
                        "inhalt": "Kontaktinformationen"
                    },
                    "segmente": [
                        {
                            "zaehler": "0260",
                            "nr": "00016",
                            "bezeichnung": "CTA",
                            "standard_status": "M",
                            "bdew_status": "M",
                            "standard_maximale_wiederholungen": 1,
                            "bdew_maximale_wiederholungen": 1,
                            "ebene": 2,
                            "inhalt": "Ansprechpartner"
                        },
                        {
                            "zaehler": "0270",
                            "nr": "00017",
                            "bezeichnung": "COM",
                            "standard_status": "C",
                            "bdew_status": "R",
                            "standard_maximale_wiederholungen": 5,
                            "bdew_maximale_wiederholungen": 5,
                            "ebene": 3,
                            "inhalt": "Kommunikationsverbindung"
                        }
                    ],
                    "segmentgruppen": []
                }
            ]
        },
        {
            "header_linie": {
                "zaehler": "0150",
                "nr": null,
                "bezeichnung": "SG3",
                "standard_status": "C",
                "bdew_status": "R",
                "standard_maximale_wiederholungen": 99,
                "bdew_maximale_wiederholungen": 1,
                "ebene": 1,
                "inhalt": "MP-ID Empf\u00e4nger"
            },
            "segmente": [
                {
                    "zaehler": "0160",
                    "nr": "00018",
                    "bezeichnung": "NAD",
                    "standard_status": "M",
                    "bdew_status": "M",
                    "standard_maximale_wiederholungen": 1,
                    "bdew_maximale_wiederholungen": 1,
                    "ebene": 1,
                    "inhalt": "MP-ID Empf\u00e4nger"
                }
            ],
            "segmentgruppen": []
        },
        {
            "header_linie": {
                "zaehler": "0150",
                "nr": null,
                "bezeichnung": "SG3",
                "standard_status": "C",
                "bdew_status": "D",
                "standard_maximale_wiederholungen": 99,
                "bdew_maximale_wiederholungen": 1,
                "ebene": 1,
                "inhalt": "Beteiligter Marktpartner MP-ID"
            },
            "segmente": [
                {
                    "zaehler": "0160",
                    "nr": "00019",
                    "bezeichnung": "NAD",
                    "standard_status": "M",
                    "bdew_status": "M",
                    "standard_maximale_wiederholungen": 1,
                    "bdew_maximale_wiederholungen": 1,
                    "ebene": 1,
                    "inhalt": "Beteiligter Marktpartner MP-ID"
                }
            ],
            "segmentgruppen": []
        },
        {
            "header_linie": {
                "zaehler": "0150",
                "nr": null,
                "bezeichnung": "SG3",
                "standard_status": "C",
                "bdew_status": "D",
                "standard_maximale_wiederholungen": 99,
                "bdew_maximale_wiederholungen": 1,
                "ebene": 1,
                "inhalt": "Name und Lieferadresse f\u00fcr Altger\u00e4te"
            },
            "segmente": [
                {
                    "zaehler": "0160",
                    "nr": "00020",
                    "bezeichnung": "NAD",
                    "standard_status": "M",
                    "bdew_status": "M",
                    "standard_maximale_wiederholungen": 1,
                    "bdew_maximale_wiederholungen": 1,
                    "ebene": 1,
                    "inhalt": "Name und Lieferadresse f\u00fcr Altger\u00e4te"
                }
            ],
            "segmentgruppen": []
        },
        {
            "header_linie": {
                "zaehler": "0320",
                "nr": null,
                "bezeichnung": "SG8",
                "standard_status": "C",
                "bdew_status": "D",
                "standard_maximale_wiederholungen": 5,
                "bdew_maximale_wiederholungen": 1,
                "ebene": 1,
                "inhalt": "W\u00e4hrungsangaben"
            },
            "segmente": [
                {
                    "zaehler": "0330",
                    "nr": "00021",
                    "bezeichnung": "CUX",
                    "standard_status": "M",
                    "bdew_status": "M",
                    "standard_maximale_wiederholungen": 1,
                    "bdew_maximale_wiederholungen": 1,
                    "ebene": 1,
                    "inhalt": "W\u00e4hrungsangaben"
                }
            ],
            "segmentgruppen": []
        },
        {
            "header_linie": {
                "zaehler": "1040",
                "nr": null,
                "bezeichnung": "SG27",
                "standard_status": "C",
                "bdew_status": "D",
                "standard_maximale_wiederholungen": 200000,
                "bdew_maximale_wiederholungen": 200000,
                "ebene": 1,
                "inhalt": "Positionsteil"
            },
            "segmente": [
                {
                    "zaehler": "1050",
                    "nr": "00022",
                    "bezeichnung": "LIN",
                    "standard_status": "M",
                    "bdew_status": "M",
                    "standard_maximale_wiederholungen": 1,
                    "bdew_maximale_wiederholungen": 1,
                    "ebene": 1,
                    "inhalt": "Positionsdaten"
                },
                {
                    "zaehler": "1210",
                    "nr": "00023",
                    "bezeichnung": "FTX",
                    "standard_status": "C",
                    "bdew_status": "D",
                    "standard_maximale_wiederholungen": 99,
                    "bdew_maximale_wiederholungen": 1,
                    "ebene": 2,
                    "inhalt": "Besondere Sachverhalte zur Sperrung (nicht pauschal im\nPreisblatt abgebildet)"
                },
                {
                    "zaehler": "1210",
                    "nr": "00024",
                    "bezeichnung": "FTX",
                    "standard_status": "C",
                    "bdew_status": "D",
                    "standard_maximale_wiederholungen": 99,
                    "bdew_maximale_wiederholungen": 1,
                    "ebene": 2,
                    "inhalt": "IP-Adresse des Absenders"
                },
                {
                    "zaehler": "1210",
                    "nr": "00025",
                    "bezeichnung": "FTX",
                    "standard_status": "C",
                    "bdew_status": "D",
                    "standard_maximale_wiederholungen": 99,
                    "bdew_maximale_wiederholungen": 1,
                    "ebene": 2,
                    "inhalt": "IP-Range des Absenders"
                }
            ],
            "segmentgruppen": []
        }
    ]
}